mate4dummies/LICENSE.txt
mate4dummies/__init__.py
mate4dummies/mate.py
mate4dummies/objects.py
mate4dummies/testing/debugger_MATE_for_Dummies.py
mate4dummies/testing/start_MATE_for_Dummies.py
mate4dummies/testing/start_MATE_for_Dummies_2.py
mate4dummies/testing/start_MATE_for_Dummies_3.py
MATE_for_Dummies-0.5.2.dist-info/LICENSE.txt
MATE_for_Dummies-0.5.2.dist-info/METADATA
MATE_for_Dummies-0.5.2.dist-info/WHEEL
MATE_for_Dummies-0.5.2.dist-info/top_level.txt
MATE_for_Dummies-0.5.2.dist-info/RECORD
