Metadata-Version: 2.1
Name: MATE-for-Dummies
Version: 0.5.2
Summary: MATE for Dummies. Scienta Omicron MATE Scripting System in Python
Home-page: https://pypi.org/project/MATE-for-Dummies/
Author: Stephan Zevenhuizen
Author-email: S.J.M.Zevenhuizen@uu.nl
License: The license file is in the package.
Keywords: SPM scanning probe microscopy
Platform: UNKNOWN
Classifier: Development Status :: 5 - Production/Stable
Classifier: Intended Audience :: Science/Research
Classifier: License :: OSI Approved :: BSD License
Classifier: Natural Language :: English
Classifier: Operating System :: Microsoft :: Windows
Classifier: Programming Language :: Python :: 3
Classifier: Topic :: Scientific/Engineering
Classifier: Topic :: Scientific/Engineering :: Chemistry
Classifier: Topic :: Scientific/Engineering :: Physics
Classifier: Topic :: Software Development :: Libraries :: Python Modules
Requires-Python: >=3.5
Requires-Dist: psutil
Requires-Dist: pefile
